ANIAnimator/__init__.py
ANIAnimator/__main__.py
ANIAnimator/core.py
ANIAnimator/helpers.py
ANIAnimator-0.2.2.dist-info/LICENSE
ANIAnimator-0.2.2.dist-info/METADATA
ANIAnimator-0.2.2.dist-info/WHEEL
ANIAnimator-0.2.2.dist-info/top_level.txt
ANIAnimator-0.2.2.dist-info/RECORD
