Metadata-Version: 2.1
Name: ANIAnimator
Version: 0.2.2
Summary: ANIAnimator makes the GIF file from a given chemical ANI file
Home-page: https://github.com/eftalgezer/ANIAnimator
Author: Eftal Gezer
Author-email: eftal.gezer@astrobiyoloji.org
Project-URL: Bug Reports, https://github.com/eftalgezer/ANIAnimator/issues
Project-URL: Source, https://github.com/eftalgezer/ANIAnimator/
Project-URL: Blog, https://beyondthearistotelian.blogspot.com/search/label/ANIAnimator
Project-URL: Developer, https://www.eftalgezer.com/
Keywords: ANI,GIF,animation,molecular calculations,chemistry,physics,ANI to GIF converter
Classifier: Development Status :: 5 - Production/Stable
Classifier: Intended Audience :: Developers
Classifier: Intended Audience :: Education
Classifier: Intended Audience :: Science/Research
Classifier: Topic :: Education
Classifier: Topic :: Multimedia :: Graphics :: Graphics Conversion
Classifier: Topic :: Scientific/Engineering
Classifier: Topic :: Scientific/Engineering :: Bio-Informatics
Classifier: Topic :: Scientific/Engineering :: Chemistry
Classifier: Topic :: Scientific/Engineering :: Physics
Classifier: License :: OSI Approved :: GNU General Public License v3 or later (GPLv3+)
Classifier: Operating System :: MacOS :: MacOS X
Classifier: Operating System :: Microsoft :: Windows
Classifier: Operating System :: POSIX :: Linux
Classifier: Programming Language :: Python :: 2
Classifier: Programming Language :: Python :: 2.7
Classifier: Programming Language :: Python :: 3
Classifier: Programming Language :: Python :: 3.1
Classifier: Programming Language :: Python :: 3.2
Classifier: Programming Language :: Python :: 3.3
Classifier: Programming Language :: Python :: 3.4
Classifier: Programming Language :: Python :: 3.5
Classifier: Programming Language :: Python :: 3.6
Classifier: Programming Language :: Python :: 3.7
Classifier: Programming Language :: Python :: 3.8
Classifier: Programming Language :: Python :: 3.9
Classifier: Programming Language :: Python :: 3.10
Classifier: Programming Language :: Python :: 3.11
License-File: LICENSE
Requires-Dist: mogli
Requires-Dist: pillow
